llama_index/vector_stores/timescalevector/__init__.py
llama_index/vector_stores/timescalevector/base.py
flying_delta_vector_stores_timescalevector-0.1.0.dist-info/METADATA
flying_delta_vector_stores_timescalevector-0.1.0.dist-info/WHEEL
flying_delta_vector_stores_timescalevector-0.1.0.dist-info/RECORD
